iss_pass_tracker/__init__.py
iss_pass_tracker/__main__.py
iss_pass_tracker/api.py
iss_pass_tracker-1.0.1.dist-info/licenses/LICENSE
iss_pass_tracker-1.0.1.dist-info/METADATA
iss_pass_tracker-1.0.1.dist-info/WHEEL
iss_pass_tracker-1.0.1.dist-info/top_level.txt
iss_pass_tracker-1.0.1.dist-info/RECORD
