Metadata-Version: 2.4
Name: iss-pass-tracker
Version: 1.0.1
Summary: Fetch upcoming ISS passes for a location and helpers to notify users.
Author-email: Sanjeet Kumar <sanjeetkumarit@gmail.com>
License: MIT
Project-URL: Homepage, https://github.com/sanjeetkumaritoutlook/iss-pass-tracker
Project-URL: Repository, https://github.com/sanjeetkumaritoutlook/iss-pass-tracker
Keywords: iss,satellite,space,tracker,open-notify
Classifier: Programming Language :: Python :: 3
Classifier: License :: OSI Approved :: MIT License
Classifier: Operating System :: OS Independent
Requires-Python: >=3.9
License-File: LICENSE
Requires-Dist: requests>=2.20.0
Provides-Extra: cli
Requires-Dist: click; extra == "cli"
Dynamic: license-file
